artist/__init__.py
artist/core/__init__.py
artist/core/core_utils.py
artist/core/heliostat_ray_tracer.py
artist/core/kinematic_reconstructor.py
artist/core/learning_rate_schedulers.py
artist/core/loss_functions.py
artist/core/motor_position_optimizer.py
artist/core/regularizers.py
artist/core/surface_reconstructor.py
artist/data_parser/__init__.py
artist/data_parser/calibration_data_parser.py
artist/data_parser/h5_scenario_parser.py
artist/data_parser/paint_calibration_parser.py
artist/data_parser/paint_scenario_parser.py
artist/data_parser/stral_scenario_parser.py
artist/field/__init__.py
artist/field/actuators.py
artist/field/actuators_ideal.py
artist/field/actuators_linear.py
artist/field/heliostat_field.py
artist/field/heliostat_group.py
artist/field/heliostat_group_rigid_body.py
artist/field/kinematic.py
artist/field/kinematic_rigid_body.py
artist/field/surface.py
artist/field/tower_target_areas.py
artist/scenario/__init__.py
artist/scenario/configuration_classes.py
artist/scenario/h5_scenario_generator.py
artist/scenario/scenario.py
artist/scenario/surface_generator.py
artist/scene/__init__.py
artist/scene/light_source.py
artist/scene/light_source_array.py
artist/scene/rays.py
artist/scene/sun.py
artist/util/__init__.py
artist/util/config_dictionary.py
artist/util/environment_setup.py
artist/util/index_mapping.py
artist/util/nurbs.py
artist/util/raytracing_utils.py
artist/util/type_mappings.py
artist/util/utils.py
artist_csp-1.0.0.dist-info/METADATA
artist_csp-1.0.0.dist-info/WHEEL
artist_csp-1.0.0.dist-info/licenses/LICENSE.md
artist_csp-1.0.0.dist-info/licenses/NOTICE
artist_csp-1.0.0.dist-info/RECORD
