Metadata-Version: 2.4
Name: artist-csp
Version: 1.0.0
Summary: AI-enhanced Differentiable Ray Tracer for Irradiation Prediction in Solar Tower Digital Twins
Project-URL: Homepage, https://github.com/ARTIST-Association/ARTIST
Project-URL: Issues, https://github.com/ARTIST-Association/ARTIST/issues
Author-email: ARTIST Consortium <artist@lists.kit.edu>
License-File: LICENSE.md
License-File: NOTICE
Classifier: Development Status :: 1 - Planning
Classifier: License :: OSI Approved :: MIT License
Classifier: Programming Language :: Python :: 3
Requires-Python: >=3.10
Requires-Dist: colorlog
Requires-Dist: h5py
Requires-Dist: numpy
Requires-Dist: paint-csp
Requires-Dist: pillow
Requires-Dist: torch
Provides-Extra: dev
Requires-Dist: pre-commit; extra == 'dev'
Requires-Dist: pytest; extra == 'dev'
Requires-Dist: pytest-cov; extra == 'dev'
Requires-Dist: pytest-mock; extra == 'dev'
Requires-Dist: ruff; extra == 'dev'
Requires-Dist: sphinx-autoapi; extra == 'dev'
Requires-Dist: sphinx-rtd-theme; extra == 'dev'
Requires-Dist: sphinxcontrib-napoleon; extra == 'dev'
Requires-Dist: sphinxemoji; extra == 'dev'
Provides-Extra: examples
Requires-Dist: matplotlib; extra == 'examples'
Requires-Dist: mpi4py; extra == 'examples'
Requires-Dist: pandas; extra == 'examples'
Requires-Dist: propulate; extra == 'examples'
Provides-Extra: tutorials
Requires-Dist: matplotlib; extra == 'tutorials'
